[
  {
    "title": "晶科能源午后涨幅扩大至10%",
    "link": "https://www.36kr.com/newsflashes/3668531752379016",
    "desc": "",
    "source": "36Kr 快讯",
    "ts": "2026-02-04T05:05:19.208Z"
  },
  {
    "title": "韩国养老基金计划今年发行美元债券",
    "link": "https://www.36kr.com/newsflashes/3668521653887881",
    "desc": "",
    "source": "36Kr 快讯",
    "ts": "2026-02-04T05:05:19.208Z"
  },
  {
    "title": "国家药监局：“十五五”期间将大力支持生物制造产业创新发展",
    "link": "https://www.36kr.com/newsflashes/3668507101782660",
    "desc": "",
    "source": "36Kr 快讯",
    "ts": "2026-02-04T05:05:19.208Z"
  },
  {
    "title": "贝恩资本收购日本美妆护理品牌集团FineToday Holdings",
    "link": "https://www.36kr.com/newsflashes/3668499074474625",
    "desc": "",
    "source": "36Kr 快讯",
    "ts": "2026-02-04T05:05:19.208Z"
  },
  {
    "title": "阿里国际站：春节期间外贸订单可由平台帮忙发货",
    "link": "https://www.36kr.com/newsflashes/3668488714969733",
    "desc": "",
    "source": "36Kr 快讯",
    "ts": "2026-02-04T05:05:19.208Z"
  },
  {
    "title": "腾讯元宝AI红包分享已更改为“口令红包”",
    "link": "https://www.36kr.com/newsflashes/3668480153101189",
    "desc": "",
    "source": "36Kr 快讯",
    "ts": "2026-02-04T05:05:19.208Z"
  },
  {
    "title": "恒生指数午间休盘跌0.41%，恒生科技指数跌2.2%",
    "link": "https://www.36kr.com/newsflashes/3668470995264133",
    "desc": "",
    "source": "36Kr 快讯",
    "ts": "2026-02-04T05:05:19.208Z"
  },
  {
    "title": "东营银行注册资本增至48.4亿元",
    "link": "https://www.36kr.com/newsflashes/3668457993347720",
    "desc": "",
    "source": "36Kr 快讯",
    "ts": "2026-02-04T05:05:19.208Z"
  },
  {
    "title": "半日主力资金加仓电力设备股，抛售电子股",
    "link": "https://www.36kr.com/newsflashes/3668457183617666",
    "desc": "",
    "source": "36Kr 快讯",
    "ts": "2026-02-04T05:05:19.208Z"
  },
  {
    "title": "香港高院驳回许家印针对接管人任命上诉申请，并令其2月20日前支付120万港元诉讼费，否则将丧失辩护权",
    "link": "https://www.36kr.com/newsflashes/3668450009031557",
    "desc": "",
    "source": "36Kr 快讯",
    "ts": "2026-02-04T05:05:19.208Z"
  },
  {
    "title": "A股三大指数午间休盘集体下跌，煤炭股大涨",
    "link": "https://www.36kr.com/newsflashes/3668441569403779",
    "desc": "",
    "source": "36Kr 快讯",
    "ts": "2026-02-04T05:05:19.208Z"
  },
  {
    "title": "“千顾科技”获7亿元C轮融资",
    "link": "https://www.36kr.com/newsflashes/3668430893720451",
    "desc": "",
    "source": "36Kr 快讯",
    "ts": "2026-02-04T05:05:19.208Z"
  },
  {
    "title": "文远知行注册资本增至40亿元",
    "link": "https://www.36kr.com/newsflashes/3668428213527172",
    "desc": "",
    "source": "36Kr 快讯",
    "ts": "2026-02-04T05:05:19.208Z"
  },
  {
    "title": "水贝会回应小程序暂停服务：正在配合资料更新与重审",
    "link": "https://www.36kr.com/newsflashes/3668424208966528",
    "desc": "",
    "source": "36Kr 快讯",
    "ts": "2026-02-04T05:05:19.208Z"
  },
  {
    "title": "脑机海河实验室团队研发的全国首个“中医脑机接口”装备\"神工-华佗\" 在津落地",
    "link": "https://www.36kr.com/newsflashes/3668418189959810",
    "desc": "",
    "source": "36Kr 快讯",
    "ts": "2026-02-04T05:05:19.208Z"
  }
]