[
  {
    "title": "热门中概股美股盘前涨跌不一，阿里巴巴跌超2%",
    "link": "https://www.36kr.com/newsflashes/3667584584885124",
    "desc": "",
    "source": "36Kr 快讯",
    "ts": "2026-02-03T20:27:19.620Z"
  },
  {
    "title": "美股大型科技股盘前普涨，英特尔涨超3%",
    "link": "https://www.36kr.com/newsflashes/3667576829911943",
    "desc": "",
    "source": "36Kr 快讯",
    "ts": "2026-02-03T20:27:19.620Z"
  },
  {
    "title": "惠普任命临时首席执行官",
    "link": "https://www.36kr.com/newsflashes/3667562553090946",
    "desc": "",
    "source": "36Kr 快讯",
    "ts": "2026-02-03T20:27:19.620Z"
  },
  {
    "title": "奈飞联席CEO就收购华纳兄弟交易遭美国参议院委员会质询",
    "link": "https://www.36kr.com/newsflashes/3667537577862024",
    "desc": "",
    "source": "36Kr 快讯",
    "ts": "2026-02-03T20:27:19.620Z"
  },
  {
    "title": "瑞银：存储芯片2028年才有可能出现有意义的供给缓解",
    "link": "https://www.36kr.com/newsflashes/3667533457236873",
    "desc": "",
    "source": "36Kr 快讯",
    "ts": "2026-02-03T20:27:19.620Z"
  },
  {
    "title": "2025年我国规上轻工业增加值同比增长5.3%",
    "link": "https://www.36kr.com/newsflashes/3667558526591876",
    "desc": "",
    "source": "36Kr 快讯",
    "ts": "2026-02-03T20:27:19.620Z"
  },
  {
    "title": "辉瑞第四季度营收175.6亿美元",
    "link": "https://www.36kr.com/newsflashes/3667530958742408",
    "desc": "",
    "source": "36Kr 快讯",
    "ts": "2026-02-03T20:27:19.620Z"
  },
  {
    "title": "中央网信办召开《生活服务类平台算法负面清单（试行）》推进部署会议",
    "link": "https://www.36kr.com/newsflashes/3667553391403910",
    "desc": "",
    "source": "36Kr 快讯",
    "ts": "2026-02-03T20:27:19.620Z"
  },
  {
    "title": "燕麦科技：公司收购的AXIS-TEC具有硅光晶圆测试相关产品",
    "link": "https://www.36kr.com/newsflashes/3667551253226120",
    "desc": "",
    "source": "36Kr 快讯",
    "ts": "2026-02-03T20:27:19.620Z"
  },
  {
    "title": "西门子能源将在美国投资10亿美元",
    "link": "https://www.36kr.com/newsflashes/3667529785697158",
    "desc": "",
    "source": "36Kr 快讯",
    "ts": "2026-02-03T20:27:19.620Z"
  },
  {
    "title": "凯龙高科：拟购买金旺达70%股权，2月4日复牌",
    "link": "https://www.36kr.com/newsflashes/3667520487940739",
    "desc": "",
    "source": "36Kr 快讯",
    "ts": "2026-02-03T20:27:19.620Z"
  },
  {
    "title": "默沙东第四季度净利润29.63亿美元，同比减少21%",
    "link": "https://www.36kr.com/newsflashes/3667519215837826",
    "desc": "",
    "source": "36Kr 快讯",
    "ts": "2026-02-03T20:27:19.620Z"
  },
  {
    "title": "印度最高法院质疑WhatsApp与Meta实体共享用户数据政策",
    "link": "https://www.36kr.com/newsflashes/3667515387192193",
    "desc": "",
    "source": "36Kr 快讯",
    "ts": "2026-02-03T20:27:19.620Z"
  },
  {
    "title": "智洋创新：筹划购买灵明光子控制权 股票停牌",
    "link": "https://www.36kr.com/newsflashes/3667509657674371",
    "desc": "",
    "source": "36Kr 快讯",
    "ts": "2026-02-03T20:27:19.620Z"
  },
  {
    "title": "百事公司第四季度净营收293.4亿美元，同比增长5.6%",
    "link": "https://www.36kr.com/newsflashes/3667497827033736",
    "desc": "",
    "source": "36Kr 快讯",
    "ts": "2026-02-03T20:27:19.620Z"
  },
  {
    "title": "江苏某高校要求教学老师像行政老师一样「朝九晚五」，为什么要这样做？负责教学科研的老师有必要「坐班」吗？",
    "link": "https://www.zhihu.com/question/2002063451275691627",
    "desc": "",
    "source": "知乎热榜",
    "ts": "2026-02-03T20:27:18.217Z"
  },
  {
    "title": "「男子强奸嫂子后杀人未遂、出狱后又刺死阻拦者」案再审改判死刑，此案在法律上有哪些特殊之处？",
    "link": "https://www.zhihu.com/question/2002052517899494764",
    "desc": "",
    "source": "知乎热榜",
    "ts": "2026-02-03T20:27:18.217Z"
  },
  {
    "title": "如何评价2026年2月米哈游《原神》璃月古诗《琅风 兹白》？",
    "link": "https://www.zhihu.com/question/2001969998810342884",
    "desc": "",
    "source": "知乎热榜",
    "ts": "2026-02-03T20:27:18.217Z"
  },
  {
    "title": "如何看待美国白宫正就稳定币收益问题与稳定币公司和银行进行会谈？有利息就没有 100% 存款准备金率？",
    "link": "https://www.zhihu.com/question/2001952470549624363",
    "desc": "",
    "source": "知乎热榜",
    "ts": "2026-02-03T20:27:18.217Z"
  },
  {
    "title": "黄金重回 4800 美元，此前跌至 4400 美元，白银涨超 6%，日韩股市高开高走，市场企稳了吗？",
    "link": "https://www.zhihu.com/question/2001945303557891756",
    "desc": "",
    "source": "知乎热榜",
    "ts": "2026-02-03T20:27:18.217Z"
  },
  {
    "title": "周生生挂坠刮出白痕，不同点位金含量差异超35%，部分点位含铁银钯，金饰中为何会有这些元素？这算足金吗？",
    "link": "https://www.zhihu.com/question/2001775737003271008",
    "desc": "",
    "source": "知乎热榜",
    "ts": "2026-02-03T20:27:18.217Z"
  },
  {
    "title": "上海启动「收购二手住房用作保障性租赁房」工作，会给住房市场带来哪些变化？",
    "link": "https://www.zhihu.com/question/2001720705633507147",
    "desc": "",
    "source": "知乎热榜",
    "ts": "2026-02-03T20:27:18.217Z"
  },
  {
    "title": "小鹏机器人假人疑云后再翻车，线下首秀摔趴被抬走，问题可能出在哪里？双足机器人保持平衡到底有多难？",
    "link": "https://www.zhihu.com/question/2001257534565150999",
    "desc": "",
    "source": "知乎热榜",
    "ts": "2026-02-03T20:27:18.217Z"
  },
  {
    "title": "内蒙古一银行员工诱导11位储户将220万元转其他「高息储蓄」然后挥霍，储户告银行败诉，法律依据是什么？",
    "link": "https://www.zhihu.com/question/2001218732253525675",
    "desc": "",
    "source": "知乎热榜",
    "ts": "2026-02-03T20:27:18.217Z"
  },
  {
    "title": "华大集团 CEO 称长期负面情绪会导致脑部生理性改变，有科学依据吗？哪些方法可以减缓这种改变？",
    "link": "https://www.zhihu.com/question/2000562858031801809",
    "desc": "",
    "source": "知乎热榜",
    "ts": "2026-02-03T20:27:18.217Z"
  },
  {
    "title": "老同学室友遇到了难事需要借两万块钱，我满口答应了，可是家人反对，我该怎么办？",
    "link": "https://www.zhihu.com/question/2000118799601508900",
    "desc": "",
    "source": "知乎热榜",
    "ts": "2026-02-03T20:27:18.217Z"
  },
  {
    "title": "如何应对过度共情带来的情绪负担？以前对我很不好的一个人，当他露出可怜脆弱的神情，我也会跟着难受怎么办？",
    "link": "https://www.zhihu.com/question/2000011864566948387",
    "desc": "",
    "source": "知乎热榜",
    "ts": "2026-02-03T20:27:18.217Z"
  },
  {
    "title": "离职当天就把工作群默默退完了，做错了吗？",
    "link": "https://www.zhihu.com/question/2000001511061730184",
    "desc": "",
    "source": "知乎热榜",
    "ts": "2026-02-03T20:27:18.217Z"
  },
  {
    "title": "1 克黄金能打一张完整黄金婚书引热议，黄金的延展性到底有多强？金价飙升，这种轻量奢华蕴藏多大商业空间？",
    "link": "https://www.zhihu.com/question/1999853061464614005",
    "desc": "",
    "source": "知乎热榜",
    "ts": "2026-02-03T20:27:18.217Z"
  },
  {
    "title": "2026 年中央一号文件发布，首提「常态化精准帮扶」，如何解读？还有哪些新的举措值得关注？",
    "link": "https://www.zhihu.com/question/2002083195005474767",
    "desc": "",
    "source": "知乎热榜",
    "ts": "2026-02-03T20:27:18.216Z"
  }
]