[
  {
    "title": "商务部回应对美农产品关税问题",
    "link": "https://www.36kr.com/newsflashes/3878170856648710",
    "desc": "商务部新闻发言人何亚东在7月2日举行的例行发布会上回应有关降低或取消对美国农产品关税的提问时说，农产品贸易是中美经贸合作的重要组成部分。经过近期经贸磋商，双方设定了扩大农产品双向贸",
    "source": "36Kr 快讯",
    "ts": "2026-07-02T07:22:59.591Z"
  },
  {
    "title": "美光CEO再次暗讽苹果：低价采购是造成内存短缺的关键",
    "link": "https://www.36kr.com/newsflashes/3878168457310211",
    "desc": "美光科技首席执行官最新表示，过去几年里，一些客户要求内存制造商降低价格，从而带来了一些负面影响。2023年美光的价格降到了原来的1/3，导致无力投资新的产能。美光的这番暗讽被普遍认",
    "source": "36Kr 快讯",
    "ts": "2026-07-02T07:22:59.591Z"
  },
  {
    "title": "郭明錤：亚马逊消费电子产品转向自研处理器优化成本结构",
    "link": "https://www.36kr.com/newsflashes/3878165706977541",
    "desc": "分析师郭明錤表示，亚马逊为备战持续的AI基建浪潮计划自研消费电子产品处理器，以图降低芯片成本，为AI投资留出足够资金。亚马逊的自由现金流在2026年Q1仅有12亿美元上下。亚马逊计",
    "source": "36Kr 快讯",
    "ts": "2026-07-02T07:22:59.591Z"
  },
  {
    "title": "“高云半导体”完成数亿元Pre-IPO轮融资",
    "link": "https://www.36kr.com/newsflashes/3878165063725065",
    "desc": "36氪获悉，“高云半导体”宣布完成Pre-IPO轮融资交割落地。本次融资总规模达数亿元。本次Pre-IPO轮融资由广开基金、广州工控资本、越秀产业基金、广州金控基金、知识城创投、国",
    "source": "36Kr 快讯",
    "ts": "2026-07-02T07:22:59.591Z"
  },
  {
    "title": "商务部：中欧于今秋举行贸易投资磋商机制第二次例会",
    "link": "https://www.36kr.com/newsflashes/3878162623590657",
    "desc": "商务部新闻发言人何亚东在2日举行的例行新闻发布会上介绍中欧贸易投资磋商机制首次会议情况时说，中欧贸易投资磋商机制是中欧在经贸领域新建立的常态化交流机制，双方商定每年举行1至2次部长",
    "source": "36Kr 快讯",
    "ts": "2026-07-02T07:22:59.591Z"
  },
  {
    "title": "韩国化妆品上半年出口额70亿美元，创历年同期新高",
    "link": "https://www.36kr.com/newsflashes/3878160726519817",
    "desc": "据韩国食品医药品安全处2日发布的初步统计，今年上半年韩国化妆品出口额同比增加27.3%，为70亿美元，创下历年同期最高纪录。以上半年为准，化妆品出口额2022年至2024年连续三年",
    "source": "36Kr 快讯",
    "ts": "2026-07-02T07:22:59.591Z"
  },
  {
    "title": "丰田反向进口美产“汉兰达”8月在日本全国发售",
    "link": "https://www.36kr.com/newsflashes/3878156362149895",
    "desc": "丰田汽车公司7月1日宣布，8月1日将在日本全国发售反向进口的美产SUV“汉兰达”，该车型4月已在东京率先发售，此次将发售的是混合动力车（HV），售价860万日元（约合人民币36万元",
    "source": "36Kr 快讯",
    "ts": "2026-07-02T07:22:59.591Z"
  },
  {
    "title": "A股三大指数集体收跌，半导体板块下挫",
    "link": "https://www.36kr.com/newsflashes/3878153843191813",
    "desc": "36氪获悉，A股三大指数集体收跌，沪指跌2.03%，深成指跌3.85%，创业板指跌5.71%；电脑硬件、半导体、通信设备板块领跌，神工股份、澜起科技跌超14%，天孚通信跌超12%，",
    "source": "36Kr 快讯",
    "ts": "2026-07-02T07:22:59.591Z"
  },
  {
    "title": "智元机器人成立智能设备新公司，注册资本450万",
    "link": "https://www.36kr.com/newsflashes/3878147165712392",
    "desc": "36氪获悉，天眼查App显示，7月2日，智元创新（上海）智能设备有限公司成立，法定代表人为邓泰华，注册资本450万人民币，经营范围包括智能机器人的研发、人工智能硬件销售、人工智能基",
    "source": "36Kr 快讯",
    "ts": "2026-07-02T07:22:59.591Z"
  },
  {
    "title": "中合担保在上海成立咨询公司，注册资本100万",
    "link": "https://www.36kr.com/newsflashes/3878138847555593",
    "desc": "36氪获悉，天眼查App显示，近日，上海中合明智企业咨询有限公司成立，法定代表人为王炯，注册资本100万人民币，经营范围包括企业管理咨询、企业管理、信息咨询服务、企业形象策划、市场",
    "source": "36Kr 快讯",
    "ts": "2026-07-02T07:22:59.591Z"
  },
  {
    "title": "美政府正与AI公司协商自愿性安全标准，最快下周公布",
    "link": "https://www.36kr.com/newsflashes/3878134592172035",
    "desc": "随着美国政府试图为开发前沿人工智能系统的公司建立更可预测的框架，政府方面预计最快将于下周起推出针对先进人工智能模型的自愿性标准。报道称，美政府官员们目前正在与领先的AI企业合作讨论",
    "source": "36Kr 快讯",
    "ts": "2026-07-02T07:22:59.591Z"
  },
  {
    "title": "道达尔能源以3.5亿美元出售马来西亚Marjoram气田权益给INPEX",
    "link": "https://www.36kr.com/newsflashes/3878131671773448",
    "desc": "道达尔能源7月2日宣布，已同意将其持有的马来西亚海上2E区块85%权益出售给日本国际石油开发帝石公司（INPEX），交易对价为3.5亿美元。该交易对应道达尔能源在Marjoram天",
    "source": "36Kr 快讯",
    "ts": "2026-07-02T07:22:59.591Z"
  },
  {
    "title": "秒悟Meoo上线Night Plan",
    "link": "https://www.36kr.com/newsflashes/3878124300660995",
    "desc": "36氪获悉，据阿里云消息，秒悟Meoo上线Night Plan：每晚22:00至次日08:00（北京时间），用户在meoo.com网页端选用指定模型发起对话，系统将自动按错峰价计费",
    "source": "36Kr 快讯",
    "ts": "2026-07-02T07:22:59.591Z"
  },
  {
    "title": "沪深两市成交额突破3万亿",
    "link": "https://www.36kr.com/newsflashes/3878118277984257",
    "desc": "36氪获悉，沪深两市成交额突破3万亿，较上日此时缩量超2700亿。",
    "source": "36Kr 快讯",
    "ts": "2026-07-02T07:22:59.591Z"
  },
  {
    "title": "苹果据悉今年计划生产1000万部折叠屏iPhone",
    "link": "https://www.36kr.com/newsflashes/3878116698845442",
    "desc": "7月2日，据报道，苹果公司已告知供应商为今年生产约1000万部可折叠iPhone做准备，这高于此前预估的700万-800万部。苹果还计划今年下半年和明年上半年推出至少5款新机型。（",
    "source": "36Kr 快讯",
    "ts": "2026-07-02T07:22:59.591Z"
  }
]