[
  {
    "title": "新易盛：整体来看，二季度业绩预告情况与公司年初对全年整体情况的预期基本吻合",
    "link": "https://www.36kr.com/newsflashes/3903985686824841",
    "desc": "新易盛近日在电话会议上表示，整体来看，二季度业绩预告情况与公司年初对全年整体情况的预期基本吻合，利润增长的核心驱动力包括以下几方面：1. 订单层面：订单交付需求的增长，预计下半年订",
    "source": "36Kr 快讯",
    "ts": "2026-07-20T13:49:48.320Z"
  },
  {
    "title": "年内A股公司累计回购金额超过800亿元",
    "link": "https://www.36kr.com/newsflashes/3903983734540168",
    "desc": "数据显示，截至7月20日，A股市场年内已有超800家公司实施回购，合计回购金额816.67亿元。美的集团、京东方A、顺丰控股、贵州茅台、紫金矿业年内回购金额均超过20亿元。（证券时",
    "source": "36Kr 快讯",
    "ts": "2026-07-20T13:49:48.320Z"
  },
  {
    "title": "热门中概股美股盘前普涨，阿里巴巴涨超3%",
    "link": "https://www.36kr.com/newsflashes/3903981840696969",
    "desc": "36氪获悉， 热门中概股美股盘前普涨，截至发稿，阿里巴巴、百度涨超3%，京东、网易涨超2%，拼多多、哔哩哔哩、蔚来涨超1%，理想汽车涨0.81%。",
    "source": "36Kr 快讯",
    "ts": "2026-07-20T13:49:48.320Z"
  },
  {
    "title": "美股大型科技股盘前多数上涨，闪迪涨超3%",
    "link": "https://www.36kr.com/newsflashes/3903980483331717",
    "desc": "36氪获悉，美股大型科技股盘前多数上涨，截至发稿，闪迪、美光科技涨超3%，英特尔涨超2%，英伟达涨超1%特斯拉涨0.89%，谷歌涨0.5%，亚马逊涨0.35%，Meta涨0.1%；",
    "source": "36Kr 快讯",
    "ts": "2026-07-20T13:49:48.320Z"
  },
  {
    "title": "“尼卡光学”完成近亿元A轮融资",
    "link": "https://www.36kr.com/newsflashes/3903974776292998",
    "desc": "36氪获悉，全息技术领域企业“尼卡光学”宣布完成近亿元A轮融资。本轮融资由中银国际投资、天津滨海产业基金、Gobi Partners、中信建投、珠海全志科技等机构共同投资。融资资金",
    "source": "36Kr 快讯",
    "ts": "2026-07-20T13:49:48.320Z"
  },
  {
    "title": "曝零一万物启动新一轮融资，拟2027年申请IPO",
    "link": "https://www.36kr.com/newsflashes/3903968879511169",
    "desc": "据报道，由国际知名人工智能专家李开复创立的零一万物正推进融资计划，并计划在2027年进行申请首次公开募股（IPO）。据悉，李开复计划在零一万物首次公布年度业绩前后完成这轮融资，但未",
    "source": "36Kr 快讯",
    "ts": "2026-07-20T13:49:48.320Z"
  },
  {
    "title": "招商证券终止为中韩半导体等6只基金提供主做市服务，回应：单纯商业行为，非市场方向判断",
    "link": "https://www.36kr.com/newsflashes/3903961766037124",
    "desc": "近日，上交所公告称，经招商证券股份有限公司备案申请，自2026年7月20日起，招商证券终止为6只QDII基金提供主做市服务。对此，招商证券20日回复称，这只是单纯的商业行为，不涉及",
    "source": "36Kr 快讯",
    "ts": "2026-07-20T13:49:48.320Z"
  },
  {
    "title": "淘天集团公布四项AIGX技术体系最新技术成果",
    "link": "https://www.36kr.com/newsflashes/3903953892050823",
    "desc": "36氪获悉，7月20日，淘天集团公布了AIGX技术体系的四项最新技术成果，包括拍立淘全模态实时Agent、全场景AI创作工作台if Studio、Coupella智惠引擎和Agen",
    "source": "36Kr 快讯",
    "ts": "2026-07-20T13:49:48.320Z"
  },
  {
    "title": "智明达：因特殊事项影响，公司特种领域获取订单受限三年",
    "link": "https://www.36kr.com/newsflashes/3903957327628160",
    "desc": "36氪获悉，智明达公告，公司近日获悉，因特殊事项影响，从即日起三年，公司在特种领域获取订单受限，预计对公司生产经营和财务状况产生一定负面影响。目前公司整体生产经营活动正常，已签订的",
    "source": "36Kr 快讯",
    "ts": "2026-07-20T13:49:48.320Z"
  },
  {
    "title": "光轮智能与西门子正式达成合作",
    "link": "https://www.36kr.com/newsflashes/3903949369329280",
    "desc": "36氪获悉，近日，在WAIC 2026现场，光轮智能与西门子正式达成合作。双方将依托光轮智能的三位一体全栈自研仿真平台SimFoundry，推动工业软件中长期积累的物理模型、工程参",
    "source": "36Kr 快讯",
    "ts": "2026-07-20T13:49:48.320Z"
  },
  {
    "title": "三环集团：拟以4.5亿元至9亿元回购股份",
    "link": "https://www.36kr.com/newsflashes/3903936026969990",
    "desc": "36氪获悉，三环集团公告，公司拟以自有资金或自筹资金回购股份，回购资金总额不低于4.5亿元且不超过9亿元，回购价格不超过135元/股。回购股份将用于股权激励计划或员工持股计划、维护",
    "source": "36Kr 快讯",
    "ts": "2026-07-20T13:49:48.320Z"
  },
  {
    "title": "雷迪克：实际控制人沈仁荣因非公司事项收到取保候审决定书",
    "link": "https://www.36kr.com/newsflashes/3903936486213254",
    "desc": "36氪获悉，雷迪克公告，公司实际控制人、董事长兼总经理沈仁荣于2026年7月20日收到杭州市公安局出具的《取保候审决定书》，因涉嫌内幕交易被取保候审，期限自2026年7月20日起算",
    "source": "36Kr 快讯",
    "ts": "2026-07-20T13:49:48.320Z"
  },
  {
    "title": "波音CEO：在推出新款客机前，公司还需数年时间修复财务状况",
    "link": "https://www.36kr.com/newsflashes/3903919044298626",
    "desc": "波音首席执行官凯利・奥特伯格周一接受美国消费者新闻与商业频道采访时表示，这家飞机制造商在研发推出全新商用客机之前，还需要 “好几年” 修复自身财务体系。奥特伯格称，各家航司客户都希",
    "source": "36Kr 快讯",
    "ts": "2026-07-20T13:49:48.320Z"
  },
  {
    "title": "美国汽油均价重回每加仑4美元高位",
    "link": "https://www.36kr.com/newsflashes/3903922915559044",
    "desc": "美国汽车协会发布的数据显示，全美普通汽油平均价格20日再次上涨至每加仑4美元以上水平。这一价格去年同期为每加仑3.14美元。此前，受美国和伊朗军事冲突等因素影响，全美普通汽油平均价",
    "source": "36Kr 快讯",
    "ts": "2026-07-20T13:49:48.320Z"
  },
  {
    "title": "中国与泰国签署加强产供链经济合作的谅解备忘录",
    "link": "https://www.36kr.com/newsflashes/3903921640474240",
    "desc": "36氪获悉，据商务部消息，在国务院总理李强和泰国总理阿努廷共同见证下，中国商务部部长王文涛与泰国副总理兼商业部长素帕姬在北京签署了《中华人民共和国商务部和泰王国商业部关于加强产供链",
    "source": "36Kr 快讯",
    "ts": "2026-07-20T13:49:48.320Z"
  },
  {
    "title": "香港演员、谢霆锋父亲谢贤去世，他在影坛留下了哪些经典作品？你对他有哪些记忆？",
    "link": "https://www.zhihu.com/question/2062563035739156529",
    "desc": "据港媒，一代红星“四哥”谢贤今日（20日）传出离世噩耗，享年89岁，《星岛头条》报道称，正在内地筹备于7月25至26日举行演唱会的儿子谢霆锋，已紧急低调返回香港，为爸爸谢贤处理后事",
    "source": "知乎热榜",
    "ts": "2026-07-20T13:49:47.688Z"
  },
  {
    "title": "余文乐宣布离婚，其 2017 年与妻子结婚育有一儿一女，怎样看待他们的婚姻？",
    "link": "https://www.zhihu.com/question/2062540964820772002",
    "desc": "20日，余文樂发文：“我们达成共识，尊重并祝福彼此的人生选择。感谢你作为妈妈作为妻子付出的所有，往后我们永远是家人。”据悉，余文乐2017年宣布与王棠云结婚，婚后育有一儿一女。 刚",
    "source": "知乎热榜",
    "ts": "2026-07-20T13:49:47.688Z"
  },
  {
    "title": "如何评价代数几何著名猜想「雅可比猜想」被AI证伪？如此简洁、可独立验证的数学发现意味着什么？",
    "link": "https://www.zhihu.com/question/2062518030224061737",
    "desc": "北京时间2026年7月20日，雅可比猜想被找到反例：",
    "source": "知乎热榜",
    "ts": "2026-07-20T13:49:47.688Z"
  },
  {
    "title": "中国肯德基「炸鸡配西瓜」促销引发美国网友热议，品牌本土化营销需要考虑其他国家的文化禁忌吗？",
    "link": "https://www.zhihu.com/question/2062469683769336787",
    "desc": "有外国博主在社交平台发帖称，发现中国肯德基推出了「炸鸡配西瓜」促销活动，引来不少外国网友围观。有美国网友留言称，这样的搭配如果出现在美国，可能会被贴上种族主义的标签；也有人表示，看",
    "source": "知乎热榜",
    "ts": "2026-07-20T13:49:47.688Z"
  },
  {
    "title": "沪指、创业板指收红，电力、煤炭板块走强，如何看待 2026 年 7 月 20 日 A 股市场行情？",
    "link": "https://www.zhihu.com/question/2062469292113891730",
    "desc": "7月20日，市场尾盘拉升，沪指、创业板指、科创50指数探底回升翻红。沪深两市成交额2.7万亿元，较上一个交易日放量472亿元。盘面上，市场热点较为杂乱，全市场超3700只个股下跌，",
    "source": "知乎热榜",
    "ts": "2026-07-20T13:49:47.688Z"
  },
  {
    "title": "西班牙队仅失一球，创造世界杯冠军球队单届最少失球纪录，怎样评价他们在 2026 美加墨世界杯的表现？",
    "link": "https://www.zhihu.com/question/2062433435608506955",
    "desc": "在刚刚结束的美加墨世界杯决赛中，西班牙队通过加时赛以1:0战胜卫冕冠军阿根廷队，继2010年南非世界杯后，队史第二次夺冠。#西班牙vs阿根廷# 西班牙队曾在2008年和2010年连",
    "source": "知乎热榜",
    "ts": "2026-07-20T13:49:47.688Z"
  },
  {
    "title": "姆巴佩 10 球夺世界杯金靴，并以 22 球登顶世界杯历史总射手榜，想超越他有多难？",
    "link": "https://www.zhihu.com/question/2062431941387710588",
    "desc": "2026年美加墨世界杯决赛战罢，本届赛事的射手榜正式尘埃落定。姆巴佩以10粒进球领跑射手榜，成功摘得世界杯金靴，同时以22粒世界杯总进球登顶世界杯历史总射手榜。梅西打入8粒进球，位",
    "source": "知乎热榜",
    "ts": "2026-07-20T13:49:47.688Z"
  },
  {
    "title": "西班牙中场罗德里获 2026 世界杯金球奖，怎样评价他在本届比赛中的表现？对于西班牙队有多重要？",
    "link": "https://www.zhihu.com/question/2062428579145540871",
    "desc": "直播吧07月20日讯 2026美加墨世界杯落幕，冠军球队西班牙的中场核心罗德里荣膺世界杯金球奖！冠军核心！官方：30岁西班牙中场罗德里荣膺2026世界杯金球奖-直播吧手机版",
    "source": "知乎热榜",
    "ts": "2026-07-20T13:49:47.688Z"
  },
  {
    "title": "中国国新、中国诚通深夜发声，增持中国股票资产，释放什么信号？",
    "link": "https://www.zhihu.com/question/2062331320521450737",
    "desc": "7月19日晚间，两大国有资本运营平台同步发布重磅增持公告：中国国新已动用超500亿元再贷款及配套资金增持央企股票，中国诚通亦累计投入近百亿元布局央企与科技资产；两家机构均明确将持续",
    "source": "知乎热榜",
    "ts": "2026-07-20T13:49:47.688Z"
  },
  {
    "title": "一年超 8 万家面包店关停，超市烘焙区却排长队，面包生意到底好不好做？反映了怎样的消费趋势？",
    "link": "https://www.zhihu.com/question/2062293737414160723",
    "desc": "谁能想到，曾经遍地开花、排队疯抢的面包店，如今正在大批量退场：一边是上市烘焙龙头业绩大跌，老牌、网红烘焙连锁接连闭店收缩；另一边是商超烘焙档口天天挤满人，网红面包、蛋糕卖到断货。同",
    "source": "知乎热榜",
    "ts": "2026-07-20T13:49:47.688Z"
  },
  {
    "title": "4.4版本戎韬将军爻光被抹除，后续剧情她还能回来吗？",
    "link": "https://www.zhihu.com/question/2062292051006428752",
    "desc": "不要啊，我的爻老板，快回来和我们爻一爻！",
    "source": "知乎热榜",
    "ts": "2026-07-20T13:49:47.688Z"
  },
  {
    "title": "如何评价张凌赫、王楚然主演的民国剧《这一秒过火》？",
    "link": "https://www.zhihu.com/question/2062177306093925253",
    "desc": "剧集根据匪我思存原著小说《如果这一秒，我没有遇见你》改编。",
    "source": "知乎热榜",
    "ts": "2026-07-20T13:49:47.688Z"
  },
  {
    "title": "全美出现数据中心出售潮，「反数据中心运动」又向红蓝州同时蔓延，这会对市场和AI产业形成多大影响？",
    "link": "https://www.zhihu.com/question/2062127994513183627",
    "desc": "美国反数据中心运动蔓延向全国 AI基建热潮遭遇阻力_腾讯新闻美国数据中心出售潮",
    "source": "知乎热榜",
    "ts": "2026-07-20T13:49:47.688Z"
  },
  {
    "title": "如何看待游戏主播旭旭宝宝因发表「不看周星驰新片」观点遭网暴，发视频怒怼网友且拒绝道歉，后又将视频删除？",
    "link": "https://www.zhihu.com/question/2062096553184120966",
    "desc": "近日，主播旭旭宝宝在直播中表达了“只对周星驰主演电影感兴趣，不打算去影院看《功夫女足》”的个人观点，随即遭到大量网友的指责。 之后其发布强硬视频，把解释拍成宣战书，大范围AOE怒骂",
    "source": "知乎热榜",
    "ts": "2026-07-20T13:49:47.688Z"
  },
  {
    "title": "谢贤遗嘱将 90% 遗产留给两个孙子，剩下 10% 由其儿女平均分配，如何看这一分配？",
    "link": "https://www.zhihu.com/question/2062582137845278413",
    "desc": "7月20日下午，谢霆锋发文宣布父亲离世。据港媒报道，谢贤已完成遗产分割，并签署遗嘱。该遗产价值超过1亿港元，包括房产、股票、投资和版权。 在他的遗嘱中，他将大部分遗产留给了他的两个",
    "source": "知乎热榜",
    "ts": "2026-07-20T13:49:47.687Z"
  }
]