[
  {
    "title": "机构：特朗普拟上调汽车关税，或使德国产值损失近 180 亿美元",
    "link": "https://www.36kr.com/newsflashes/3791849172589577",
    "desc": "一家经济机构周六分析称，美国总统唐纳德・特朗普宣布对欧盟汽车和卡车加征关税，或导致德国产值损失近150亿欧元（约175.8亿美元）。基尔世界经济研究所（IfW）的这一估算，凸显了欧",
    "source": "36Kr 快讯",
    "ts": "2026-05-02T08:57:37.972Z"
  },
  {
    "title": "科创板向新向优活力蓬勃，2025年净利大增26%",
    "link": "https://www.36kr.com/newsflashes/3791833394027784",
    "desc": "截至2026年4月30日，科创板608家公司披露了2025年营收15985.96亿元，同比增长10.3%；净利润586.24亿元，同比增长26.6%；研发投入1892.47亿元，连",
    "source": "36Kr 快讯",
    "ts": "2026-05-02T08:57:37.972Z"
  },
  {
    "title": "特朗普政府救助计划失败，美国精神航空宣布停止运营",
    "link": "https://www.36kr.com/newsflashes/3791782399991047",
    "desc": "陷入困境的美国廉价航空公司精神航空周六表示，已开始有序地逐步停止运营。精神航空表示，所有航班均已取消，已建议乘客不要前往机场。 此前特朗普政府曾考虑向精神航空提供5亿美元，以换取该",
    "source": "36Kr 快讯",
    "ts": "2026-05-02T08:57:37.972Z"
  },
  {
    "title": "“五一”假期运输火车票已售1.17亿张",
    "link": "https://www.36kr.com/newsflashes/3791855130369033",
    "desc": "从国铁集团获悉，截至今天8时，“五一”假期运输火车票已经发售1.17亿张。（央视新闻）",
    "source": "36Kr 快讯",
    "ts": "2026-05-02T08:57:37.972Z"
  },
  {
    "title": "雅诗兰黛：中国大陆连续五个季度市场份额增长",
    "link": "https://www.36kr.com/newsflashes/3791843421002760",
    "desc": "36氪获悉，5月1日，雅诗兰黛集团公布了2026财年第三季度财报。报告期内，公司净销售额增长5%，达到37亿美元；有机净销售额增长2%；调整后毛利率增加140个基点，从75.0%增",
    "source": "36Kr 快讯",
    "ts": "2026-05-02T08:57:37.972Z"
  },
  {
    "title": "WildFire Energy股东正寻求按逾40亿美元出售该美国页岩油运营商",
    "link": "https://www.36kr.com/newsflashes/3791697672527104",
    "desc": "据知情人士透露，投资公司华平投资（Warburg Pincus）和凯恩安德森（Kayne Anderson）正在探索出售WildFire Energy的可能性，预计任何交易对这家美",
    "source": "36Kr 快讯",
    "ts": "2026-05-02T08:57:37.972Z"
  },
  {
    "title": "日本央行前行长黑田东彦称2%的通胀目标已实现",
    "link": "https://www.36kr.com/newsflashes/3791696180059392",
    "desc": "日本央行前行长黑田东彦表示，日本央行已经实现2%的通胀目标，日本不需要财政扩张或货币宽松政策。黑田东彦表示，在通胀与经济放缓风险并存的情况下，日本央行4月28日选择暂不加息是正确的",
    "source": "36Kr 快讯",
    "ts": "2026-05-02T08:57:37.972Z"
  },
  {
    "title": "2026年五一档新片票房突破3亿元",
    "link": "https://www.36kr.com/newsflashes/3791810462555140",
    "desc": "36氪获悉，据灯塔专业版，截至5月2日15时02分，2026年五一档新片总票房（含点映及预售）突破3亿元，《寒战1994》《消失的人》《穿普拉达的女王2》《10间敢死队》《给阿嬷的",
    "source": "36Kr 快讯",
    "ts": "2026-05-02T08:57:37.972Z"
  },
  {
    "title": "国际海事组织决定加开会议商讨净零排放框架",
    "link": "https://www.36kr.com/newsflashes/3791671614462984",
    "desc": "国际海事组织海上环境保护委员会第84届会议5月1日决定，拟在委员会第85届会议召开前举行两次船舶温室气体减排工作组会议，进一步研究对国际海事组织净零排放框架的相关关切。委员会决定，",
    "source": "36Kr 快讯",
    "ts": "2026-05-02T08:57:37.972Z"
  },
  {
    "title": "LABUBU冰箱二手价回落，一夜跌10000元",
    "link": "https://www.36kr.com/newsflashes/3791787182710017",
    "desc": "近日，泡泡玛特首款冷藏箱开售，官方发售价5999元。各平台都有不同程度的溢价，此前有媒体注意到，LABUBU冰箱的转售报价已达到19999元。5月1日，记者查询发现，LABUBU冰",
    "source": "36Kr 快讯",
    "ts": "2026-05-02T08:57:37.972Z"
  },
  {
    "title": "“五一”假期首日高速公路充电量同比增长55.6%",
    "link": "https://www.36kr.com/newsflashes/3791783404166402",
    "desc": "36氪获悉，国家能源局数据显示，“五一”假期首日，全国高速公路迎来出行高峰。国家能源局提前部署、精准施策，指导各地提前开展服务区充电设施检修维护，加强充电车辆调度引导，全力保障人民",
    "source": "36Kr 快讯",
    "ts": "2026-05-02T08:57:37.972Z"
  },
  {
    "title": "全球第四大黄金矿业公司据悉暂停IPO计划",
    "link": "https://www.36kr.com/newsflashes/3791652713602312",
    "desc": "据知情人士透露，纳沃伊矿业冶金公司（Navoi Mining &amp; Metallurgical Co.）的首次公开募股工作已经暂停，因为乌兹别克斯坦政府正在权衡何时才是让这家",
    "source": "36Kr 快讯",
    "ts": "2026-05-02T08:57:37.972Z"
  },
  {
    "title": "百亿私募一季报调仓换股情况曝光",
    "link": "https://www.36kr.com/newsflashes/3791651881966595",
    "desc": "随着上市公司2026年一季报披露完毕，百亿私募的调仓换股情况也浮出水面。今年一季度，高毅资产邓晓峰减持京东方A、TCL科技；高毅资产冯柳减持海康威视，逆市加仓瑞丰新材；杨东掌舵的宁",
    "source": "36Kr 快讯",
    "ts": "2026-05-02T08:57:37.972Z"
  },
  {
    "title": "上海迎来首票非洲20个国家零关税项下商品",
    "link": "https://www.36kr.com/newsflashes/3791598580489481",
    "desc": "从上海海关获悉，5月1日凌晨，上海迎来首票对同中国建交的20个不属于最不发达国家的非洲国家实施零关税项下商品。这批商品为总重516吨、来自埃及的鲜橙，通过海运入境，在上海海关所属上",
    "source": "36Kr 快讯",
    "ts": "2026-05-02T08:57:37.972Z"
  },
  {
    "title": "巴西石油公司第一季度对美出口降至零",
    "link": "https://www.36kr.com/newsflashes/3791572988828935",
    "desc": "巴西石油公司Petrobras已将其对美国的石油出口削减至零。今年第一季度，这家国有石油公司约62%的外运原油流向了中国。1-3月期间，巴西石油公司平均每日出口约112万桶石油及衍",
    "source": "36Kr 快讯",
    "ts": "2026-05-02T08:57:37.972Z"
  }
]