[
  {
    "title": "VinFast：加速布局东南亚市场，拟2027年前建立数百家零售网点",
    "link": "https://www.36kr.com/newsflashes/3665714845540992",
    "desc": "",
    "source": "36Kr 快讯",
    "ts": "2026-02-02T05:20:00.781Z"
  },
  {
    "title": "苏州：2025年全市实现地区生产总值27695.1亿元，同比增长5.4%",
    "link": "https://www.36kr.com/newsflashes/3665709491315336",
    "desc": "",
    "source": "36Kr 快讯",
    "ts": "2026-02-02T05:20:00.781Z"
  },
  {
    "title": "三星SDI第四季度电池销售额3.62万亿韩元",
    "link": "https://www.36kr.com/newsflashes/3665701656322690",
    "desc": "",
    "source": "36Kr 快讯",
    "ts": "2026-02-02T05:20:00.781Z"
  },
  {
    "title": "本立科技：副总经理盛孟均因个人原因辞职",
    "link": "https://www.36kr.com/newsflashes/3665691691869061",
    "desc": "",
    "source": "36Kr 快讯",
    "ts": "2026-02-02T05:20:00.781Z"
  },
  {
    "title": "2025年保险业保费收入同比增长7.43%，总资产实现两位数增长",
    "link": "https://www.36kr.com/newsflashes/3665679431950982",
    "desc": "",
    "source": "36Kr 快讯",
    "ts": "2026-02-02T05:20:00.781Z"
  },
  {
    "title": "德明利：产品暂未涉及人形机器人领域",
    "link": "https://www.36kr.com/newsflashes/3665667624034951",
    "desc": "",
    "source": "36Kr 快讯",
    "ts": "2026-02-02T05:20:00.781Z"
  },
  {
    "title": "特斯拉：第三代特斯拉人形机器人即将亮相，预计年产百万台",
    "link": "https://www.36kr.com/newsflashes/3665650452882312",
    "desc": "",
    "source": "36Kr 快讯",
    "ts": "2026-02-02T05:20:00.781Z"
  },
  {
    "title": "半日主力资金加仓电力设备股，抛售电子股",
    "link": "https://www.36kr.com/newsflashes/3665643395637896",
    "desc": "",
    "source": "36Kr 快讯",
    "ts": "2026-02-02T05:20:00.781Z"
  },
  {
    "title": "现货白银价格小幅反弹后日内第二次下跌超10%",
    "link": "https://www.36kr.com/newsflashes/3665642833388420",
    "desc": "",
    "source": "36Kr 快讯",
    "ts": "2026-02-02T05:20:00.781Z"
  },
  {
    "title": "恒指午间休盘跌2.4%，恒生科技指数跌3.68%",
    "link": "https://www.36kr.com/newsflashes/3665640316429184",
    "desc": "",
    "source": "36Kr 快讯",
    "ts": "2026-02-02T05:20:00.781Z"
  },
  {
    "title": "九部门：持续完善银行卡、移动支付、现金服务等支付环境，便利春节期间入境游客支付",
    "link": "https://www.36kr.com/newsflashes/3665624111325826",
    "desc": "",
    "source": "36Kr 快讯",
    "ts": "2026-02-02T05:20:00.781Z"
  },
  {
    "title": "国家人工智能产业投资基金入股新芯航途",
    "link": "https://www.36kr.com/newsflashes/3665623586022016",
    "desc": "",
    "source": "36Kr 快讯",
    "ts": "2026-02-02T05:20:00.781Z"
  },
  {
    "title": "交易员们称印度央行通过海外渠道抛售美元以支撑卢比",
    "link": "https://www.36kr.com/newsflashes/3665612069184391",
    "desc": "",
    "source": "36Kr 快讯",
    "ts": "2026-02-02T05:20:00.781Z"
  },
  {
    "title": "九部门：鼓励金融机构与重点商户合作策划春节专属活动，推出消费红包、消费立减等优惠",
    "link": "https://www.36kr.com/newsflashes/3665616683606664",
    "desc": "",
    "source": "36Kr 快讯",
    "ts": "2026-02-02T05:20:00.781Z"
  },
  {
    "title": "A股三大指数午间休盘集体下跌，资源股走弱",
    "link": "https://www.36kr.com/newsflashes/3665611271971712",
    "desc": "",
    "source": "36Kr 快讯",
    "ts": "2026-02-02T05:20:00.781Z"
  }
]