[
  {
    "title": "“无限宇航”完成Pre-A轮融资",
    "link": "https://www.36kr.com/newsflashes/3549384375021700",
    "desc": "",
    "source": "36Kr 快讯",
    "ts": "2025-11-12T01:00:58.493Z"
  },
  {
    "title": "华泰证券：家电板块估值与成长双线驱动，建议沿三条主线布局",
    "link": "https://www.36kr.com/newsflashes/3549382089126016",
    "desc": "",
    "source": "36Kr 快讯",
    "ts": "2025-11-12T01:00:58.493Z"
  },
  {
    "title": "AMD预计数据中心产品需求将推动营收加速增长",
    "link": "https://www.36kr.com/newsflashes/3549380258197632",
    "desc": "",
    "source": "36Kr 快讯",
    "ts": "2025-11-12T01:00:58.493Z"
  },
  {
    "title": "特朗普计划与杰米·戴蒙及华尔街高管共进晚餐",
    "link": "https://www.36kr.com/newsflashes/3549378663788672",
    "desc": "",
    "source": "36Kr 快讯",
    "ts": "2025-11-12T01:00:58.493Z"
  },
  {
    "title": "银河证券：算力板块依然处于业绩兑现阶段",
    "link": "https://www.36kr.com/newsflashes/3549376101232769",
    "desc": "",
    "source": "36Kr 快讯",
    "ts": "2025-11-12T01:00:58.493Z"
  },
  {
    "title": "中信证券2026年社会服务业投资策略：重视景气边际变化，看好龙头兑现增长",
    "link": "https://www.36kr.com/newsflashes/3549375297433472",
    "desc": "",
    "source": "36Kr 快讯",
    "ts": "2025-11-12T01:00:58.493Z"
  },
  {
    "title": "波音10月交付53架飞机",
    "link": "https://www.36kr.com/newsflashes/3549374977454209",
    "desc": "",
    "source": "36Kr 快讯",
    "ts": "2025-11-12T01:00:58.493Z"
  },
  {
    "title": "中信证券2026年租赁住房行业投资策略：市场空间巨大，结构重估持久",
    "link": "https://www.36kr.com/newsflashes/3549374511984518",
    "desc": "",
    "source": "36Kr 快讯",
    "ts": "2025-11-12T01:00:58.493Z"
  },
  {
    "title": "两市融资余额增加40.22亿元",
    "link": "https://www.36kr.com/newsflashes/3549374102679430",
    "desc": "",
    "source": "36Kr 快讯",
    "ts": "2025-11-12T01:00:58.493Z"
  },
  {
    "title": "消息称三星电子为晶圆代工业务设立2027年目标：重返盈利、市占达20%",
    "link": "https://www.36kr.com/newsflashes/3549373413355656",
    "desc": "",
    "source": "36Kr 快讯",
    "ts": "2025-11-12T01:00:58.493Z"
  },
  {
    "title": "深交所：港股通标的证券名单调整，调出康基医疗",
    "link": "https://www.36kr.com/newsflashes/3549372362977154",
    "desc": "",
    "source": "36Kr 快讯",
    "ts": "2025-11-12T01:00:58.493Z"
  },
  {
    "title": "星球石墨：公司石墨设备可以应用于磷酸铁锂、电解液等锂电池材料的生产环节",
    "link": "https://www.36kr.com/newsflashes/3549366548983682",
    "desc": "",
    "source": "36Kr 快讯",
    "ts": "2025-11-12T01:00:58.493Z"
  },
  {
    "title": "特朗普：关于咖啡，我们将下调部分关税",
    "link": "https://www.36kr.com/newsflashes/3549362892304512",
    "desc": "",
    "source": "36Kr 快讯",
    "ts": "2025-11-12T01:00:58.493Z"
  },
  {
    "title": "中信建投化工2026年投资策略展望：反内卷加速周期拐点到来，新材料仍是长期战略方向",
    "link": "https://www.36kr.com/newsflashes/3549358999318403",
    "desc": "",
    "source": "36Kr 快讯",
    "ts": "2025-11-12T01:00:58.493Z"
  },
  {
    "title": "天风证券：当前煤制气再度迎来产业催化节点",
    "link": "https://www.36kr.com/newsflashes/3549358474620806",
    "desc": "",
    "source": "36Kr 快讯",
    "ts": "2025-11-12T01:00:58.493Z"
  }
]