[
  {
    "title": "恒指收跌0.33%，恒生科技指数跌1.26%",
    "link": "https://www.36kr.com/newsflashes/3528573679000456",
    "desc": "",
    "source": "36Kr 快讯",
    "ts": "2025-10-28T08:18:02.444Z"
  },
  {
    "title": "凯辉基金独家投资“知微行易”数亿元人民币",
    "link": "https://www.36kr.com/newsflashes/3528567426325382",
    "desc": "",
    "source": "36Kr 快讯",
    "ts": "2025-10-28T08:18:02.444Z"
  },
  {
    "title": "上海医药：溴吡斯的明缓释片获得批准生产",
    "link": "https://www.36kr.com/newsflashes/3528561575746697",
    "desc": "",
    "source": "36Kr 快讯",
    "ts": "2025-10-28T08:18:02.444Z"
  },
  {
    "title": "报告：蚂蚁AQ位列中国AI原生应用榜第7，行业增速第一",
    "link": "https://www.36kr.com/newsflashes/3528559698172807",
    "desc": "",
    "source": "36Kr 快讯",
    "ts": "2025-10-28T08:18:02.444Z"
  },
  {
    "title": "中国电影：第三季度净利润1.77亿元，同比增长1463.17%",
    "link": "https://www.36kr.com/newsflashes/3528555676998533",
    "desc": "",
    "source": "36Kr 快讯",
    "ts": "2025-10-28T08:18:02.444Z"
  },
  {
    "title": "小米高层调整：中国区总裁王晓雁不再兼任小米之家总经理，陈恺接任",
    "link": "https://www.36kr.com/newsflashes/3528551047273608",
    "desc": "",
    "source": "36Kr 快讯",
    "ts": "2025-10-28T08:18:02.444Z"
  },
  {
    "title": "游族网络旗下公司等在无锡成立云星智算投资合伙企业，出资额约66.7亿元",
    "link": "https://www.36kr.com/newsflashes/3528545678482313",
    "desc": "",
    "source": "36Kr 快讯",
    "ts": "2025-10-28T08:18:02.444Z"
  },
  {
    "title": "富瀚微向港交所提交上市申请",
    "link": "https://www.36kr.com/newsflashes/3528544278469506",
    "desc": "",
    "source": "36Kr 快讯",
    "ts": "2025-10-28T08:18:02.444Z"
  },
  {
    "title": "世界坝体最高抽水蓄能电站全面投产发电",
    "link": "https://www.36kr.com/newsflashes/3528541944667270",
    "desc": "",
    "source": "36Kr 快讯",
    "ts": "2025-10-28T08:18:02.444Z"
  },
  {
    "title": "日本交易员的瑞士法郎空仓规模创新高，几乎是年初水平两倍",
    "link": "https://www.36kr.com/newsflashes/3528535761411204",
    "desc": "",
    "source": "36Kr 快讯",
    "ts": "2025-10-28T08:18:02.444Z"
  },
  {
    "title": "长沙战新引领产业投资基金成立，出资额10亿元",
    "link": "https://www.36kr.com/newsflashes/3528534138477447",
    "desc": "",
    "source": "36Kr 快讯",
    "ts": "2025-10-28T08:18:02.444Z"
  },
  {
    "title": "巴克莱8亿美元收购美国个人贷款平台Best Egg",
    "link": "https://www.36kr.com/newsflashes/3528532589665416",
    "desc": "",
    "source": "36Kr 快讯",
    "ts": "2025-10-28T08:18:02.444Z"
  },
  {
    "title": "河北幸福消费金融公司注册资本增至10亿，增幅约57%",
    "link": "https://www.36kr.com/newsflashes/3528530638789766",
    "desc": "",
    "source": "36Kr 快讯",
    "ts": "2025-10-28T08:18:02.444Z"
  },
  {
    "title": "韩国央行时隔多年考虑中长期增持黄金储备",
    "link": "https://www.36kr.com/newsflashes/3528526036097921",
    "desc": "",
    "source": "36Kr 快讯",
    "ts": "2025-10-28T08:18:02.444Z"
  },
  {
    "title": "比亚迪9月在欧新车注册量同比增长近四倍",
    "link": "https://www.36kr.com/newsflashes/3528523550530439",
    "desc": "",
    "source": "36Kr 快讯",
    "ts": "2025-10-28T08:18:02.444Z"
  }
]