[
  {
    "title": "2026春节档观影人次破亿",
    "link": "https://www.36kr.com/newsflashes/3694281180917381",
    "desc": "",
    "source": "36Kr 快讯",
    "ts": "2026-02-22T16:19:59.095Z"
  },
  {
    "title": "印度贸易代表团推迟访美",
    "link": "https://www.36kr.com/newsflashes/3694238171917959",
    "desc": "",
    "source": "36Kr 快讯",
    "ts": "2026-02-22T16:19:59.095Z"
  },
  {
    "title": "春运过半 全国铁路累计发送旅客2.58亿人次",
    "link": "https://www.36kr.com/newsflashes/3694079146913413",
    "desc": "",
    "source": "36Kr 快讯",
    "ts": "2026-02-22T16:19:59.095Z"
  },
  {
    "title": "Boss直聘开源模型Nanbeige4.1-3B登顶HuggingFace文本趋势榜",
    "link": "https://www.36kr.com/newsflashes/3694196677111684",
    "desc": "",
    "source": "36Kr 快讯",
    "ts": "2026-02-22T16:19:59.095Z"
  },
  {
    "title": "美国洛杉矶港负责人：美总统加征关税加剧企业不确定性",
    "link": "https://www.36kr.com/newsflashes/3694077739921286",
    "desc": "",
    "source": "36Kr 快讯",
    "ts": "2026-02-22T16:19:59.095Z"
  },
  {
    "title": "韩国主要钢铁企业去年营业收入普遍下滑",
    "link": "https://www.36kr.com/newsflashes/3694068967075458",
    "desc": "",
    "source": "36Kr 快讯",
    "ts": "2026-02-22T16:19:59.095Z"
  },
  {
    "title": "奥尔特曼感叹：中国技术进步“快得惊人”",
    "link": "https://www.36kr.com/newsflashes/3694067607809927",
    "desc": "",
    "source": "36Kr 快讯",
    "ts": "2026-02-22T16:19:59.095Z"
  },
  {
    "title": "交通运输部：今日跨区域人员流动量将达客流峰值",
    "link": "https://www.36kr.com/newsflashes/3694000159534729",
    "desc": "",
    "source": "36Kr 快讯",
    "ts": "2026-02-22T16:19:59.095Z"
  },
  {
    "title": "截至2025年底，我国80%以上粗钢产能实现超低排放",
    "link": "https://www.36kr.com/newsflashes/3693998749151104",
    "desc": "",
    "source": "36Kr 快讯",
    "ts": "2026-02-22T16:19:59.095Z"
  },
  {
    "title": "降门槛、扩范围，新一轮设备更新已陆续启动",
    "link": "https://www.36kr.com/newsflashes/3693884082876292",
    "desc": "",
    "source": "36Kr 快讯",
    "ts": "2026-02-22T16:19:59.095Z"
  },
  {
    "title": "全球在建最大混合式抽水蓄能电站迎双突破",
    "link": "https://www.36kr.com/newsflashes/3693885455330944",
    "desc": "",
    "source": "36Kr 快讯",
    "ts": "2026-02-22T16:19:59.095Z"
  },
  {
    "title": "国开行2025年发放公路基础设施贷款超3600亿元",
    "link": "https://www.36kr.com/newsflashes/3693881635270534",
    "desc": "",
    "source": "36Kr 快讯",
    "ts": "2026-02-22T16:19:59.095Z"
  },
  {
    "title": "德国总理回应美国最高法院关于特朗普关税裁决：这是个“好消息”",
    "link": "https://www.36kr.com/newsflashes/3693882941075076",
    "desc": "",
    "source": "36Kr 快讯",
    "ts": "2026-02-22T16:19:59.095Z"
  },
  {
    "title": "马蜂窝2026春节旅游大数据：在长假效应推动下，5天以上的长线出游订单量占比达到59.6%",
    "link": "https://www.36kr.com/newsflashes/3693938109099913",
    "desc": "",
    "source": "36Kr 快讯",
    "ts": "2026-02-22T16:19:59.095Z"
  },
  {
    "title": "今天全国高速公路车流量超7100万辆次",
    "link": "https://www.36kr.com/newsflashes/3693880481197704",
    "desc": "",
    "source": "36Kr 快讯",
    "ts": "2026-02-22T16:19:59.095Z"
  },
  {
    "title": "2026 LCK 第一赛段季后赛 DK 让二追三淘汰 T1，如何评价这场比赛？",
    "link": "https://www.zhihu.com/question/2009003507722781653",
    "desc": "",
    "source": "知乎热榜",
    "ts": "2026-02-22T16:19:57.847Z"
  },
  {
    "title": "新加坡大满贯首日，温瑞博 0-3 不敌张禹珍，如何评价他在比赛中的表现？",
    "link": "https://www.zhihu.com/question/2008904645481890674",
    "desc": "",
    "source": "知乎热榜",
    "ts": "2026-02-22T16:19:57.847Z"
  },
  {
    "title": "如何看待阿耳忒弥斯2号绕月任务将进行火箭回撤优化，取消原定2026年3月的发射？",
    "link": "https://www.zhihu.com/question/2008824486363940300",
    "desc": "",
    "source": "知乎热榜",
    "ts": "2026-02-22T16:19:57.847Z"
  },
  {
    "title": "7 名中国游客贝加尔湖遇难，未通过正规旅行社报名，车辆属非法载客，有哪些警示意义？当地管理有哪些问题？",
    "link": "https://www.zhihu.com/question/2008821216954246406",
    "desc": "",
    "source": "知乎热榜",
    "ts": "2026-02-22T16:19:57.847Z"
  },
  {
    "title": "米兰冬奥自由式滑雪女子 U 型场地技巧决赛，谷爱凌卫冕，李方慧摘银，如何评价他们的发挥？",
    "link": "https://www.zhihu.com/question/2008677675422672634",
    "desc": "",
    "source": "知乎热榜",
    "ts": "2026-02-22T16:19:57.847Z"
  },
  {
    "title": "韩延哽咽恳求多给《星河入梦》有效排片，这部投资近四亿的电影为何面临排片困境？",
    "link": "https://www.zhihu.com/question/2008647492124827724",
    "desc": "",
    "source": "知乎热榜",
    "ts": "2026-02-22T16:19:57.847Z"
  },
  {
    "title": "如何看待飞碟社发布原神动画大致上线时间？",
    "link": "https://www.zhihu.com/question/2008592348859347404",
    "desc": "",
    "source": "知乎热榜",
    "ts": "2026-02-22T16:19:57.847Z"
  },
  {
    "title": "「全世界只有中国人吃炒菜」的说法准确吗，中国炒菜独特在哪？",
    "link": "https://www.zhihu.com/question/2008266587694712347",
    "desc": "",
    "source": "知乎热榜",
    "ts": "2026-02-22T16:19:57.847Z"
  },
  {
    "title": "安徽一家族 18 个家庭每家出 500 元自办「春晚」，一天内走完所有亲戚，你觉得这种过年方式怎么样？",
    "link": "https://www.zhihu.com/question/2008179866307092516",
    "desc": "",
    "source": "知乎热榜",
    "ts": "2026-02-22T16:19:57.847Z"
  },
  {
    "title": "芯片初创公司 taalas 融资 1.69 亿美元研发 AI 芯片挑战英伟达，这意味着什么？",
    "link": "https://www.zhihu.com/question/2008005974397576586",
    "desc": "",
    "source": "知乎热榜",
    "ts": "2026-02-22T16:19:57.847Z"
  },
  {
    "title": "韩寒的《飞驰人生3》为什么再一次让观众感动？",
    "link": "https://www.zhihu.com/question/2007829771191600681",
    "desc": "",
    "source": "知乎热榜",
    "ts": "2026-02-22T16:19:57.847Z"
  },
  {
    "title": "春节放假，几乎从不主动给公司任何人发祝福信息，但是这样会不会被领导认为不主动，态度不积极，不会表现？",
    "link": "https://www.zhihu.com/question/2007550783579772734",
    "desc": "",
    "source": "知乎热榜",
    "ts": "2026-02-22T16:19:57.847Z"
  },
  {
    "title": "贵州非遗传承人半年卖800只「点翠蟑螂」，如何理解这种反差美学？若人人喊打的蟑螂变好看了，你能接受吗？",
    "link": "https://www.zhihu.com/question/2007528287103051494",
    "desc": "",
    "source": "知乎热榜",
    "ts": "2026-02-22T16:19:57.847Z"
  },
  {
    "title": "《惊蛰无声》中黄凯的结局是必然的吗？",
    "link": "https://www.zhihu.com/question/2007466972095459475",
    "desc": "",
    "source": "知乎热榜",
    "ts": "2026-02-22T16:19:57.847Z"
  },
  {
    "title": "如何评价杨幂在电影《惊蛰无声》里面的表现？",
    "link": "https://www.zhihu.com/question/2007443491538632720",
    "desc": "",
    "source": "知乎热榜",
    "ts": "2026-02-22T16:19:57.847Z"
  }
]