[
  {
    "title": "世乒赛女团决赛，中国 vs 日本，怎样评价本场比赛？",
    "link": "https://www.zhihu.com/question/2036848157703628439",
    "desc": "",
    "source": "知乎热榜",
    "ts": "2026-05-10T12:58:46.491Z"
  },
  {
    "title": "世界杯中国转播费从3亿美元腰斩到1.5亿，这个报价怎么样？未来还会降价吗？",
    "link": "https://www.zhihu.com/question/2036716290836883357",
    "desc": "据每经，多家媒体披露，此次国际足联为中国内地市场开出的2026年世界杯转播权报价，最初高达2.5亿至3亿美元，折合人民币约18亿元至21亿元。但是，在市场回归理性的背景下，这份脱离",
    "source": "知乎热榜",
    "ts": "2026-05-10T12:58:46.491Z"
  },
  {
    "title": "2027亚洲杯抽签仪式结束，国足遇伊朗，如何评价本次抽签？",
    "link": "https://www.zhihu.com/question/2036707845496951361",
    "desc": "2027亚洲杯抽签仪式结束，国足遇伊朗叙利亚吉尔吉斯斯坦，如何评价本次抽签",
    "source": "知乎热榜",
    "ts": "2026-05-10T12:58:46.491Z"
  },
  {
    "title": "2026年一季度民政统计数据登记结婚169.7万对，有哪些值得关注的信息?",
    "link": "https://www.zhihu.com/question/2036550918104142850",
    "desc": "民政部5月9日发布《2026年1季度民政统计数据》显示，今年一季度，全国结婚登记169.7万对，离婚登记62.2万对。 一季度全国结婚登记169.7万对_腾讯新闻",
    "source": "知乎热榜",
    "ts": "2026-05-10T12:58:46.491Z"
  },
  {
    "title": "官方称正调查「4 只皮皮虾 1035 元」事件中司机是否带客吃回扣，若属实商家和司机会受到怎样的处罚？",
    "link": "https://www.zhihu.com/question/2036542942957892446",
    "desc": "海南三亚一海鲜店4只皮皮虾1035元事件持续引发关注。 5月9日，三亚市当地权威部门工作人员称，经初步调查，涉事海鲜店相关海鲜售价未超出调控价格，商家是明码标价， “三亚海鲜从挑选",
    "source": "知乎热榜",
    "ts": "2026-05-10T12:58:46.491Z"
  },
  {
    "title": "如何评价 Faker 和柳智敏拍摄的广告？",
    "link": "https://www.zhihu.com/question/2036509834409948829",
    "desc": "",
    "source": "知乎热榜",
    "ts": "2026-05-10T12:58:46.491Z"
  },
  {
    "title": "盲人在盲道被电动车相撞，逃逸者反骂不看路，交警已介入，逃逸者将面临什么？遇到闯道牙的车我们能做点啥？",
    "link": "https://www.zhihu.com/question/2036401885796464014",
    "desc": "新京报讯（记者裴剑飞）近日，有一位盲人短视频博主通过网络平台反映，自己在北京旅游时，在盲道上正常行走，被一辆在盲道上骑行的电动自行车撞倒，盲杖掉落，手部受伤，对方不但没有道歉，反而",
    "source": "知乎热榜",
    "ts": "2026-05-10T12:58:46.491Z"
  },
  {
    "title": "浙江杭州122件货，94件仅退款，整条街被电商店铺拉黑，为什么会这样？拉黑整个街道合理吗？",
    "link": "https://www.zhihu.com/question/2036398639141106392",
    "desc": "近日，“整条街因恶意退货太多被商家拉黑”的消息，冲上热搜。 据扬子晚报报道，5月6日，一位网友在社媒发帖称，自己在某电商平台看中了一款商品，商品界面却显示其地址无法收货。 她询问客",
    "source": "知乎热榜",
    "ts": "2026-05-10T12:58:46.491Z"
  },
  {
    "title": "如何看待消息称华为 Pura X Max 首销超越所有折叠屏手机，10 天累计激活超 20 万？",
    "link": "https://www.zhihu.com/question/2036132690630546674",
    "desc": "这是否证明阔折叠的方向是对的？是否也能证明苹果选择的第一款折叠机的方向是正确的？ 首销爆卖20万台！华为Pura X Max刷新折叠屏行业纪录",
    "source": "知乎热榜",
    "ts": "2026-05-10T12:58:46.491Z"
  },
  {
    "title": "你听过妈妈说过的最「口是心非」的一句话是什么？",
    "link": "https://www.zhihu.com/question/2036114213890953502",
    "desc": "\"我没事。\"\"你忙吧，不用管我。\"\"浪费钱，下次别买了。\"春晖妈妈可盈偷偷攒下零花钱买了双手套，妈妈嘴上说\"浪费\"，那个冬天却每天都戴着。她所有的谎言，都藏着同一句话：\"我爱你。\"",
    "source": "知乎热榜",
    "ts": "2026-05-10T12:58:46.491Z"
  },
  {
    "title": "vibe coding真的让软件开发变得没有门槛了吗？",
    "link": "https://www.zhihu.com/question/2036103696203904043",
    "desc": "有没有非程序员出身的朋友通过vibe coding开发与上线了软件的案例？或者说分享一下vibe coding的感受。",
    "source": "知乎热榜",
    "ts": "2026-05-10T12:58:46.491Z"
  },
  {
    "title": "胖东来回应王海，「不存在空调价格欺诈、套取国补资金问题」，怎样看待此次事件？",
    "link": "https://www.zhihu.com/question/2036003620202788476",
    "desc": "5月7日晚，胖东来通过官方抖音账号发布《关于“博主王海发布胖东来国补空调相关言论”的说明》，否认国补空调价格欺诈、套取国补资金等。 对于王海提出的“国补前提价、虚高补贴基数、套取国",
    "source": "知乎热榜",
    "ts": "2026-05-10T12:58:46.491Z"
  },
  {
    "title": "苹果被曝支付巨额溢价以确保 A18 Pro 芯片的供应，反映了哪些问题？成本会转嫁给用户吗？",
    "link": "https://www.zhihu.com/question/2035848170890948934",
    "desc": "财联社5月7日讯（编辑 马兰）芯片短缺推高了消费电子行业的生产成本，并可能冲击最终的消费需求，这让整个行业都充满担忧。在此之际，苹果推出的平价电脑产品MacBook Neo进一步打",
    "source": "知乎热榜",
    "ts": "2026-05-10T12:58:46.491Z"
  },
  {
    "title": "比亚迪高管回应闪充温度高伤电池，具体说了什么，打消疑虑了吗？",
    "link": "https://www.zhihu.com/question/2035827458860131259",
    "desc": "比亚迪高管回应闪充温度高伤电池 比亚迪高管回应闪充温度高伤电池",
    "source": "知乎热榜",
    "ts": "2026-05-10T12:58:46.491Z"
  },
  {
    "title": "如何看待 2026 年 5 月 10 日电影《给阿嬷的情书》排片占比大幅提升至 18.3% 左右？",
    "link": "https://www.zhihu.com/question/2035762140078942171",
    "desc": "--- 遥望当初，谁能想到呢^O^",
    "source": "知乎热榜",
    "ts": "2026-05-10T12:58:46.491Z"
  },
  {
    "title": "深圳一直播销售改装电动自行车“黑窝点”被端 12人被刑拘",
    "link": "https://www.36kr.com/newsflashes/3803077293924100",
    "desc": "自2025年12月1日电动自行车新国标全面实施以来，深圳市市场监管局共立案457宗，扣押不合格电动自行车1062辆、相关配件1656件，罚没款73.33万元，移送公安机关3宗。4月",
    "source": "36Kr 快讯",
    "ts": "2026-05-10T12:58:45.506Z"
  },
  {
    "title": "我国首条深水油气装备工艺管线智能生产线建设完成",
    "link": "https://www.36kr.com/newsflashes/3803075895631360",
    "desc": "海洋石油工程股份有限公司5月10日发布消息，我国首条深水油气装备工艺管线智能生产线在海油工程珠海深水装备制造基地建设完成，进入调试阶段。 (新华社)",
    "source": "36Kr 快讯",
    "ts": "2026-05-10T12:58:45.506Z"
  },
  {
    "title": "魏建军称胖东来真实不造假不浮夸",
    "link": "https://www.36kr.com/newsflashes/3803074827623937",
    "desc": "5月10日，长城汽车创始人、董事长魏建军称，胖东来不造假不浮夸，所有的事情是真实的。我觉得中国的企业称之说善，有契约的精神，全是底线，不是多么优秀，全是底线，我可以这么讲，人家胖东",
    "source": "36Kr 快讯",
    "ts": "2026-05-10T12:58:45.506Z"
  },
  {
    "title": "段永平又加仓茅台了",
    "link": "https://www.36kr.com/newsflashes/3803074000920326",
    "desc": "5月7日，有网友在投资平台向知名投资人段永平提问时表示，全仓持有茅台半年，犹豫是否要调仓换股。 段永平在回复中直言：“我今天还买了茅台啊，你会凌乱吗？”5月8日，他在回复另一投资者",
    "source": "36Kr 快讯",
    "ts": "2026-05-10T12:58:45.506Z"
  },
  {
    "title": "涉汉坦病毒疫情邮轮抵达西班牙特内里费岛水域",
    "link": "https://www.36kr.com/newsflashes/3803072259677698",
    "desc": "当地时间5月10日凌晨，涉汉坦病毒疫情邮轮“洪迪厄斯”号已在西班牙特内里费岛格拉纳迪利亚港水域抛锚停泊。（新华社）",
    "source": "36Kr 快讯",
    "ts": "2026-05-10T12:58:45.506Z"
  },
  {
    "title": "沙特阿美：一季度销售额达4331亿沙特里亚尔。",
    "link": "https://www.36kr.com/newsflashes/3803070054456834",
    "desc": "5月10日，沙特阿美第一季度净利润为1201.3亿沙特里亚尔。（财联社）",
    "source": "36Kr 快讯",
    "ts": "2026-05-10T12:58:45.506Z"
  },
  {
    "title": "2连板通鼎互联：海南康宁仅作为公司的光棒供应商 不存在其他合作模式",
    "link": "https://www.36kr.com/newsflashes/3803199588114181",
    "desc": "5月10日，通鼎互联公告称，公司股票于2026年5月6日至8日连续三个交易日收盘价格涨幅偏离值累计超过20%，构成异常波动。公司注意到近期市场对光纤光缆行业关注度较高，光纤产品短期",
    "source": "36Kr 快讯",
    "ts": "2026-05-10T12:58:45.505Z"
  },
  {
    "title": "宇环数控：不生产航空航天产品的零部件",
    "link": "https://www.36kr.com/newsflashes/3803198906392067",
    "desc": "5月10日，宇环数控公告称，公司股票连续三个交易日(5月6日至5月8日)收盘价格涨幅偏离值累计超过20%，属于股票交易异常波动。公司不生产航空航天产品的零部件。公司主要产品为数控磨",
    "source": "36Kr 快讯",
    "ts": "2026-05-10T12:58:45.505Z"
  },
  {
    "title": "泰坦股份：高端电子布喷气织机尚处于研发阶段 未形成任何销售收入",
    "link": "https://www.36kr.com/newsflashes/3803198288453384",
    "desc": "5月10日，泰坦股份公告称，公司股票连续3个交易日收盘价格涨幅偏离值累计超过20%，属于异常波动。公司关注到近期电子布织机概念受市场关注度较高。截至目前，公司高端电子布喷气织机尚处",
    "source": "36Kr 快讯",
    "ts": "2026-05-10T12:58:45.505Z"
  },
  {
    "title": "复星医药：控股子公司药品新增适应症获欧盟批准",
    "link": "https://www.36kr.com/newsflashes/3803197347356417",
    "desc": "复星医药公告，近日，公司控股子公司上海复宏汉霖生物技术股份有限公司及其控股子公司自主研发的斯鲁利单抗注射液（欧盟商品名：Hetronifly®）的如下两项新增适应症获欧盟委员会批准",
    "source": "36Kr 快讯",
    "ts": "2026-05-10T12:58:45.505Z"
  },
  {
    "title": "2025年度全国秋粮收购超3.38亿吨",
    "link": "https://www.36kr.com/newsflashes/3803151259966977",
    "desc": "5月10日，国家粮食和物资储备局最新发布数据显示，2025年度秋粮旺季收购于今年4月底结束，全国各类粮食经营主体累计收购秋粮超3.38亿吨，为近年来较高水平。收购总体呈现进度快、购",
    "source": "36Kr 快讯",
    "ts": "2026-05-10T12:58:45.505Z"
  },
  {
    "title": "算力、绿能协同悄然提速",
    "link": "https://www.36kr.com/newsflashes/3803150542675465",
    "desc": "5月10日，2026年，算电协同被写入政府工作报告，成为社会关注的热词。“十五五”规划纲要也明确提出，推动绿色电力与算力协同布局。记者近日走访了解到，内蒙古、宁夏、贵州等新能源富集",
    "source": "36Kr 快讯",
    "ts": "2026-05-10T12:58:45.505Z"
  },
  {
    "title": "中国新增高端聚苯乙烯规模化产能 为光学材料供应链提供新选择",
    "link": "https://www.36kr.com/newsflashes/3803149976526345",
    "desc": "5月10日，中国石油天然气股份有限公司广西石化分公司完全自主研发的光学级聚苯乙烯产品GPPS-550N实现量产。此举意味着全球光学材料供应链上，新增一个具备稳定量产能力、自主工艺和",
    "source": "36Kr 快讯",
    "ts": "2026-05-10T12:58:45.505Z"
  },
  {
    "title": "沙特阿美：即便能源供应恢复 能源体系预计也需要较长时间才能回归常态",
    "link": "https://www.36kr.com/newsflashes/3803148430204676",
    "desc": "5月10日，沙特阿美首席执行官表示，东西管道为阿美赋予了运营灵活性，已被证明是一条关键生命线。部分受影响设施在不到24至48小时内就恢复了生产；若没有前期投资和应急预案，这一过程原",
    "source": "36Kr 快讯",
    "ts": "2026-05-10T12:58:45.505Z"
  }
]