[
  {
    "title": "思仪科技创业板IPO获上市委会议通过",
    "link": "https://www.36kr.com/newsflashes/3786321568079112",
    "desc": "36氪获悉，思仪科技创业板IPO获上市委会议通过。",
    "source": "36Kr 快讯",
    "ts": "2026-04-28T10:06:34.902Z"
  },
  {
    "title": "神力股份：第一季度净利润689.04万元，同比增长1404%",
    "link": "https://www.36kr.com/newsflashes/3786317537533190",
    "desc": "36氪获悉，神力股份发布2026年一季度业绩报告。报告显示，2026年第一季度实现营业收入3.41亿元，同比增长4.41%；归属于上市公司股东的净利润为689.04万元，同比增长1",
    "source": "36Kr 快讯",
    "ts": "2026-04-28T10:06:34.902Z"
  },
  {
    "title": "*ST波导：4月30日起撤销退市风险警示，股票简称变更为波导股份",
    "link": "https://www.36kr.com/newsflashes/3786312762858499",
    "desc": "36氪获悉，*ST波导公告，公司股票将于2026年4月29日停牌一天，自4月30日起复牌并撤销退市风险警示，证券简称由“*ST波导”变更为“波导股份”，日涨跌幅限制由5%变为10%",
    "source": "36Kr 快讯",
    "ts": "2026-04-28T10:06:34.902Z"
  },
  {
    "title": "深圳市汇川技术股份有限公司向港交所提交上市申请书",
    "link": "https://www.36kr.com/newsflashes/3786310001400840",
    "desc": "36氪获悉，据港交所文件，深圳市汇川技术股份有限公司向港交所提交上市申请书，联席保荐人为摩根士丹利、国泰君安国际、美银证券、中金公司。",
    "source": "36Kr 快讯",
    "ts": "2026-04-28T10:06:34.902Z"
  },
  {
    "title": "超捷股份：商业火箭箭体结构件预计今年二季度起陆续交付",
    "link": "https://www.36kr.com/newsflashes/3786307950959618",
    "desc": "36氪获悉，超捷股份公告，公司商业航天业务主要为商业火箭箭体结构件制造，包括箭体大部段（壳段）、整流罩等。根据现有订单情况，预计今年商业航天业务订单从二季度开始陆续交付客户，主要交",
    "source": "36Kr 快讯",
    "ts": "2026-04-28T10:06:34.902Z"
  },
  {
    "title": "盈富基金获南向资金净买入41.37亿港元",
    "link": "https://www.36kr.com/newsflashes/3786303076621315",
    "desc": "南向资金净买入145.23亿港元，盈富基金、恒生中国企业、小米集团-W净买入额位列前三，分别获净买入41.37亿港元、26.40亿港元、18.09亿港元。净卖出方面，阿里巴巴-W、",
    "source": "36Kr 快讯",
    "ts": "2026-04-28T10:06:34.902Z"
  },
  {
    "title": "生益科技：第一季度净利润11.58亿元，同比增长105.47%",
    "link": "https://www.36kr.com/newsflashes/3786297463971072",
    "desc": "36氪获悉，生益科技发布2026年一季度业绩报告。报告显示，2026年第一季度实现营业收入81.41亿元，同比增长45.09%；归属于上市公司股东的净利润为11.58亿元，同比增长",
    "source": "36Kr 快讯",
    "ts": "2026-04-28T10:06:34.902Z"
  },
  {
    "title": "首旅酒店：一季度归母净利润1.69亿元，同比增长18.51%",
    "link": "https://www.36kr.com/newsflashes/3786294948371713",
    "desc": "36氪获悉，首旅酒店发布2026年一季度业绩报告。报告显示，2026年第一季度实现营业收入17.77亿元，同比增长0.66%；归属于上市公司股东的净利润1.69亿元，上年同期归属于",
    "source": "36Kr 快讯",
    "ts": "2026-04-28T10:06:34.902Z"
  },
  {
    "title": "飞猪在上海成立文化服务新公司",
    "link": "https://www.36kr.com/newsflashes/3786289872362497",
    "desc": "36氪获悉，爱企查App显示，近日，上海飞猪文化服务有限公司成立，法定代表人为郑重，注册资本100万元人民币，经营范围包括旅行社服务网点旅游招徕、咨询服务，会议及展览服务，互联网销",
    "source": "36Kr 快讯",
    "ts": "2026-04-28T10:06:34.902Z"
  },
  {
    "title": "起帆电缆：第一季度净利润9534.09万元，同比增长36.27%",
    "link": "https://www.36kr.com/newsflashes/3786289155939590",
    "desc": "36氪获悉，起帆电缆发布2026年一季度业绩报告。报告显示，2026年第一季度实现营业收入52.01亿元，同比增长26.14%；归属于上市公司股东的净利润为9534.09万元，同比",
    "source": "36Kr 快讯",
    "ts": "2026-04-28T10:06:34.902Z"
  },
  {
    "title": "比亚迪电子：一季度净利润2783万元，同比下降95.53%",
    "link": "https://www.36kr.com/newsflashes/3786282772225287",
    "desc": "36氪获悉，比亚迪电子公告，截至三月三十一日止三个月，营业额381.83亿元，同比增长3.53%；毛利19.91亿元，同比下降14.35%；母公司权益拥有人应占溢利2783万元，同",
    "source": "36Kr 快讯",
    "ts": "2026-04-28T10:06:34.902Z"
  },
  {
    "title": "中国太保：一季度归母净利润100.41亿元，同比增加4.30%",
    "link": "https://www.36kr.com/newsflashes/3786280214355200",
    "desc": "36氪获悉，中国太保发布2026年一季度业绩报告。报告显示，2026年第一季度实现营业收入925.47亿元，同比下降1.20%；归属于上市公司股东的净利润100.41亿元，上年同期",
    "source": "36Kr 快讯",
    "ts": "2026-04-28T10:06:34.902Z"
  },
  {
    "title": "拒买新闻就交税，澳洲拟向科技巨头征约2%营收税",
    "link": "https://www.36kr.com/newsflashes/3786276284587265",
    "desc": "澳大利亚政府公布法案草案，拟对Meta、谷歌等科技巨头征收新税，除非这些平台自愿与当地新闻机构签署付费协议，以应对传统媒体在数码平台冲击下面临的生存压力。据报道，根据拟议的新法律安",
    "source": "36Kr 快讯",
    "ts": "2026-04-28T10:06:34.902Z"
  },
  {
    "title": "*ST亿晶：股票被实施退市风险警示，股票复牌",
    "link": "https://www.36kr.com/newsflashes/3786272311237635",
    "desc": "36氪获悉，*ST亿晶公告，公司股票自2026年4月29日起复牌。因2025年末经审计净资产为-8936.26万元，触及退市风险警示条件，公司股票简称由“亿晶光电”变更为“*ST亿",
    "source": "36Kr 快讯",
    "ts": "2026-04-28T10:06:34.902Z"
  },
  {
    "title": "中国平安：第一季度净利润250.22亿元，同比下降7.4%",
    "link": "https://www.36kr.com/newsflashes/3786269669448710",
    "desc": "36氪获悉，中国平安发布2026年一季度业绩报告。报告显示，2026年第一季度，集团实现归属于母公司股东的营运利润407.80亿元，同比增长7.6%；截至2026年3月31日，集团",
    "source": "36Kr 快讯",
    "ts": "2026-04-28T10:06:34.902Z"
  },
  {
    "title": "14 岁少年杀害同班女同学，一审被判无期徒刑，怎样解读这一判罚？",
    "link": "https://www.zhihu.com/question/2032468877448144370",
    "desc": "2026年4月28日，云南省曲靖市中级人民法院一审公开宣判被告人蒋某某故意杀人、强奸一案，以故意杀人罪、强奸罪判处蒋某某无期徒刑，剥夺政治权利终身。 经审理查明，被告人蒋某某（时年",
    "source": "知乎热榜",
    "ts": "2026-04-28T10:06:34.201Z"
  },
  {
    "title": "如何评价《绝区零》4月28日发布的新立绘佩洛伊斯？",
    "link": "https://www.zhihu.com/question/2032434529600812707",
    "desc": "#绝区零# #法厄同# #绝区零佩洛伊斯# 代理人档案丨佩洛伊斯 攥紧天光淬过的缰绳， 被灼伤的事物不曾隐没于皮肤—— 直到重新踏上被允诺的金车。 中文CV——侯小菲/林景 ——欢",
    "source": "知乎热榜",
    "ts": "2026-04-28T10:06:34.201Z"
  },
  {
    "title": "历经世间冷暖，保留童真算不算成年人的自我救赎？",
    "link": "https://www.zhihu.com/question/2032414425378967856",
    "desc": "成年人的世界满是现实与疲惫，我们被迫成熟、学着克制。但心底的童话与纯粹，其实从未消失。 盘点温酒《嘿，小家伙》睡前小故事，如果让你选一篇用AI制作成一款剧情游戏，你想怎么设计？ 《",
    "source": "知乎热榜",
    "ts": "2026-04-28T10:06:34.201Z"
  },
  {
    "title": "多国央行集体甩卖黄金，有哪些信息值得关注？是警示信号吗？",
    "link": "https://www.zhihu.com/question/2032400582497887693",
    "desc": "又有一家央行“甩卖”黄金，今年第一季度，阿塞拜疆国家石油基金出售了约22吨黄金。根据该基金的季度报告，此次出售的黄金储备按当前价格计算价值超过30亿美元，标志着自2012年开始购入",
    "source": "知乎热榜",
    "ts": "2026-04-28T10:06:34.201Z"
  },
  {
    "title": "「探店」网红白冰偷税被查，追缴并罚款共计超 1891 万元，有哪些警示意义？",
    "link": "https://www.zhihu.com/question/2032399785731306001",
    "desc": "4月28日消息，国家税务总局公布一起偷税案件。经查，“探店”网红白冰在2021年至2024年期间通过转换收入性质、虚假申报等方式，少缴个人所得税、增值税、契税等税费共计911.18",
    "source": "知乎热榜",
    "ts": "2026-04-28T10:06:34.201Z"
  },
  {
    "title": "伊朗三阶段和平建议讨论之时，贝森特称伊朗石油工业即将崩溃，储油罐爆满、汽油短缺将出现，对此你怎么看？",
    "link": "https://www.zhihu.com/question/2032385595960451834",
    "desc": "伊朗储油罐库存持续爆满，已开始利用海上浮式油轮储油贝森特：美国实施封锁后 伊朗石油工业开始停产伊朗提出一项分三阶段解决的谈判方案",
    "source": "知乎热榜",
    "ts": "2026-04-28T10:06:34.201Z"
  },
  {
    "title": "追觅发布火箭汽车，搭载专属定制的双固体火箭助推系统，百公里加速 0.9 秒，还有哪些亮点？",
    "link": "https://www.zhihu.com/question/2032366127414599941",
    "desc": "美国时间4月27日，追觅科技在美国硅谷召开DREAME NEXT全球发布会。界面新闻在现场了解到，追觅星空计划全球首发全新一代产品Nebula NEXT 01 JET Editio",
    "source": "知乎热榜",
    "ts": "2026-04-28T10:06:34.201Z"
  },
  {
    "title": "如何看待《明末：渊虚之羽》被意大利游戏巨头以3200W收购？",
    "link": "https://www.zhihu.com/question/2032245202908346123",
    "desc": "意大利游戏发行巨头 Digital Bros 集团近日正式官宣，旗下子公司 505 Games 已完成一笔重磅收购，斥资 3200 万人民币，从成都灵泽科技（Leenzee）手中，",
    "source": "知乎热榜",
    "ts": "2026-04-28T10:06:34.201Z"
  },
  {
    "title": "美以袭击伊朗进入第 60 天，当前局势如何？还有哪些信息值得关注？",
    "link": "https://www.zhihu.com/question/2032226305366647567",
    "desc": "",
    "source": "知乎热榜",
    "ts": "2026-04-28T10:06:34.201Z"
  },
  {
    "title": "如何评价红果下架播放量 8 亿的 AI 短剧《菩提临世》？问题出在哪？AI 短剧创作要注意什么？",
    "link": "https://www.zhihu.com/question/2032163714355263384",
    "desc": "重磅信号！红果重拳下架8亿播放量AI短剧天花板《菩提临世》",
    "source": "知乎热榜",
    "ts": "2026-04-28T10:06:34.201Z"
  },
  {
    "title": "中山大学作息新方案拟将课间休息压缩到5分钟、上午加课、缩短午休，引发学生不满，你觉得这个方案怎么样？",
    "link": "https://www.zhihu.com/question/2032153399899021674",
    "desc": "[图片]",
    "source": "知乎热榜",
    "ts": "2026-04-28T10:06:34.201Z"
  },
  {
    "title": "国家发改委「禁止外资收购 Manus 项目，要求撤销交易」，此事对中国 AI 企业出海有何警示意义？",
    "link": "https://www.zhihu.com/question/2032140708430266999",
    "desc": "4月27日，外商投资安全审查工作机制办公室（国家发展改革委）依法依规对外资收购Manus项目作出禁止投资决定，要求当事人撤销该收购交易。 https://zfxxgk.ndrc.g",
    "source": "知乎热榜",
    "ts": "2026-04-28T10:06:34.201Z"
  },
  {
    "title": "巴基斯坦总统扎尔达里 4 月 25 日至 5 月 1 日来华，访问湖南和海南，有哪些信息值得关注？",
    "link": "https://www.zhihu.com/question/2032118225358598980",
    "desc": "外交部发言人林剑27日在例行记者会上答问时说，今年是中国和巴基斯坦建交75周年，中巴关系保持了高水平的良好发展势头。巴基斯坦总统扎尔达里于4月25日至5月1日来华，访问湖南省和海南",
    "source": "知乎热榜",
    "ts": "2026-04-28T10:06:34.201Z"
  },
  {
    "title": "李想称理想比上汽大众竞品至少领先两代，大众高管回应「仅价格和营销领先」，真正的「领先」有哪些衡量维度？",
    "link": "https://www.zhihu.com/question/2032096021916988183",
    "desc": "东方财经：据鞭牛士4月27日消息，近日，理想汽车CEO李想在2026北京车展参观上汽大众展台时表示，理想L9 Livis比上汽大众ID.ERA 9X至少领先两代。 对此，在上汽大众",
    "source": "知乎热榜",
    "ts": "2026-04-28T10:06:34.201Z"
  },
  {
    "title": "男子从内地偷运 51 公斤盒饭回澳门，被海关查获，为啥要专门偷运盒饭？未经检疫的熟食入境会有什么风险？",
    "link": "https://www.zhihu.com/question/2032065068477715780",
    "desc": "4月22日，澳门海关于横琴口岸截获一宗企图偷运未经检疫熟食入境的个案，在一辆轻型客车的车尾箱共查获约51公斤的熟食盒饭。涉案男子为35岁澳门居民，承认企图将未经检疫熟食饭盒收藏于车",
    "source": "知乎热榜",
    "ts": "2026-04-28T10:06:34.201Z"
  }
]