[
  {
    "title": "Kimi新一轮10亿美元融资正在进行，估值涨至180亿美元",
    "link": "https://www.36kr.com/newsflashes/3722680180521345",
    "desc": "",
    "source": "36Kr 快讯",
    "ts": "2026-03-14T12:32:09.273Z"
  },
  {
    "title": "海关总署通报进口消费品质量安全不合格典型案例",
    "link": "https://www.36kr.com/newsflashes/3722639948528260",
    "desc": "",
    "source": "36Kr 快讯",
    "ts": "2026-03-14T12:32:09.273Z"
  },
  {
    "title": "大宗食品抽检合格率连续四年超99%，食品安全总体水平持续向好",
    "link": "https://www.36kr.com/newsflashes/3722636904397444",
    "desc": "",
    "source": "36Kr 快讯",
    "ts": "2026-03-14T12:32:09.273Z"
  },
  {
    "title": "市场监管总局：2025年共查处广告违法案件4.45万件，罚没金额2.52亿元",
    "link": "https://www.36kr.com/newsflashes/3722625830206085",
    "desc": "",
    "source": "36Kr 快讯",
    "ts": "2026-03-14T12:32:09.273Z"
  },
  {
    "title": "比亚迪正在评估入局F1",
    "link": "https://www.36kr.com/newsflashes/3722623603521921",
    "desc": "",
    "source": "36Kr 快讯",
    "ts": "2026-03-14T12:32:09.273Z"
  },
  {
    "title": "多家银行出手，积存金或将“限购”",
    "link": "https://www.36kr.com/newsflashes/3722569414703746",
    "desc": "",
    "source": "36Kr 快讯",
    "ts": "2026-03-14T12:32:09.273Z"
  },
  {
    "title": "美国商务部撤回拟议的AI芯片出口管制新规",
    "link": "https://www.36kr.com/newsflashes/3722567113112199",
    "desc": "",
    "source": "36Kr 快讯",
    "ts": "2026-03-14T12:32:09.273Z"
  },
  {
    "title": "国家电网前两月固定资产投资同比增长超80%",
    "link": "https://www.36kr.com/newsflashes/3722565826869639",
    "desc": "",
    "source": "36Kr 快讯",
    "ts": "2026-03-14T12:32:09.273Z"
  },
  {
    "title": "深圳龙岗“千人龙虾大会”火爆 现场装龙虾大排长队",
    "link": "https://www.36kr.com/newsflashes/3722549121399431",
    "desc": "",
    "source": "36Kr 快讯",
    "ts": "2026-03-14T12:32:09.273Z"
  },
  {
    "title": "腾讯 “龙虾” 免费安装全国落地",
    "link": "https://www.36kr.com/newsflashes/3722547550845576",
    "desc": "",
    "source": "36Kr 快讯",
    "ts": "2026-03-14T12:32:09.273Z"
  },
  {
    "title": "每年拿出10亿元算力券，上海建立了国内最大算力调度平台",
    "link": "https://www.36kr.com/newsflashes/3722468983814785",
    "desc": "",
    "source": "36Kr 快讯",
    "ts": "2026-03-14T12:32:09.273Z"
  },
  {
    "title": "海运数据：3月1日至今仅77艘船通过霍尔木兹海峡",
    "link": "https://www.36kr.com/newsflashes/3722466269788545",
    "desc": "",
    "source": "36Kr 快讯",
    "ts": "2026-03-14T12:32:09.273Z"
  },
  {
    "title": "2026年春运长江干线进出港货物量超4亿吨",
    "link": "https://www.36kr.com/newsflashes/3722461958273414",
    "desc": "",
    "source": "36Kr 快讯",
    "ts": "2026-03-14T12:32:09.273Z"
  },
  {
    "title": "电影《奇迹梦之队》票房破1000万",
    "link": "https://www.36kr.com/newsflashes/3722457883966080",
    "desc": "",
    "source": "36Kr 快讯",
    "ts": "2026-03-14T12:32:09.273Z"
  },
  {
    "title": "94.1亿人次 2026年春运创历史新纪录",
    "link": "https://www.36kr.com/newsflashes/3722455056660871",
    "desc": "",
    "source": "36Kr 快讯",
    "ts": "2026-03-14T12:32:09.273Z"
  }
]